Flask_Excel-0.0.7.dist-info/DESCRIPTION.rst
Flask_Excel-0.0.7.dist-info/METADATA
Flask_Excel-0.0.7.dist-info/RECORD
Flask_Excel-0.0.7.dist-info/WHEEL
Flask_Excel-0.0.7.dist-info/metadata.json
Flask_Excel-0.0.7.dist-info/top_level.txt
flask_excel/__init__.py
